pystrin/__init__.py
pystrin/pystrin.py
src/__init__.py
src/pystrin.py
pystrin-0.0.6.dist-info/LICENSE
pystrin-0.0.6.dist-info/METADATA
pystrin-0.0.6.dist-info/WHEEL
pystrin-0.0.6.dist-info/top_level.txt
pystrin-0.0.6.dist-info/RECORD
