Metadata-Version: 2.1
Name: pystrin
Version: 0.0.6
Summary: A small Python package used for string interpolation
Home-page: https://github.com/campoe/pystrin
Author: Coen van Kampen
Author-email: c.m.vankampen14@gmail.com
License: MIT
Platform: UNKNOWN
Classifier: Programming Language :: Python :: 3
Classifier: License :: OSI Approved :: MIT License
Classifier: Operating System :: OS Independent
